odoo/addons/partner_deduplicate_filter/README.rst
odoo/addons/partner_deduplicate_filter/__init__.py
odoo/addons/partner_deduplicate_filter/__manifest__.py
odoo/addons/partner_deduplicate_filter/i18n/crm_deduplicate_filter.pot
odoo/addons/partner_deduplicate_filter/i18n/de.po
odoo/addons/partner_deduplicate_filter/i18n/es.po
odoo/addons/partner_deduplicate_filter/i18n/hr.po
odoo/addons/partner_deduplicate_filter/i18n/nl_NL.po
odoo/addons/partner_deduplicate_filter/i18n/partner_deduplicate_filter.pot
odoo/addons/partner_deduplicate_filter/i18n/sk.po
odoo/addons/partner_deduplicate_filter/i18n/sl.po
odoo/addons/partner_deduplicate_filter/i18n/tr.po
odoo/addons/partner_deduplicate_filter/readme/CONTRIBUTORS.rst
odoo/addons/partner_deduplicate_filter/readme/DESCRIPTION.rst
odoo/addons/partner_deduplicate_filter/readme/USAGE.rst
odoo/addons/partner_deduplicate_filter/static/description/icon.png
odoo/addons/partner_deduplicate_filter/static/description/icon.svg
odoo/addons/partner_deduplicate_filter/static/description/index.html
odoo/addons/partner_deduplicate_filter/tests/__init__.py
odoo/addons/partner_deduplicate_filter/tests/test_partner_deduplicate_filter.py
odoo/addons/partner_deduplicate_filter/wizards/__init__.py
odoo/addons/partner_deduplicate_filter/wizards/partner_merge.py
odoo/addons/partner_deduplicate_filter/wizards/partner_merge_view.xml
odoo12_addon_partner_deduplicate_filter-12.0.1.0.0.99.dev3.dist-info/METADATA
odoo12_addon_partner_deduplicate_filter-12.0.1.0.0.99.dev3.dist-info/WHEEL
odoo12_addon_partner_deduplicate_filter-12.0.1.0.0.99.dev3.dist-info/top_level.txt
odoo12_addon_partner_deduplicate_filter-12.0.1.0.0.99.dev3.dist-info/RECORD
